mac_t.cpython-39-x86_64-linux-gnu.so
mac_t.pyi
mac_t-0.1.0.dist-info/LICENSE
mac_t-0.1.0.dist-info/WHEEL
mac_t-0.1.0.dist-info/RECORD
mac_t-0.1.0.dist-info/METADATA
mac_t-0.1.0.dist-info/top_level.txt
