Metadata-Version: 2.1
Name: mac-t
Version: 0.1.0
Summary: class for MAC(Media Access Control)
Author: skrab-sah
Author-email: skrab.sah@gmail.com
Classifier: Operating System :: POSIX :: Linux
Classifier: License :: OSI Approved :: MIT License
License-File: LICENSE
